AUTHORS.rst
CONTRIBUTING.rst
HISTORY.rst
LICENSE
MANIFEST.in
Makefile
README.rst
requirements.txt
setup.py
abcpmc/__init__.py
abcpmc/mpi_util.py
abcpmc/sampler.py
abcpmc/threshold.py
abcpmc.egg-info/PKG-INFO
abcpmc.egg-info/SOURCES.txt
abcpmc.egg-info/dependency_links.txt
abcpmc.egg-info/not-zip-safe
abcpmc.egg-info/pbr.json
abcpmc.egg-info/requires.txt
abcpmc.egg-info/top_level.txt
docs/Makefile
docs/abcpmc.png
docs/abcpmc.rst
docs/authors.rst
docs/check_sphinx.py
docs/conf.py
docs/contributing.rst
docs/history.rst
docs/index.rst
docs/installation.rst
docs/modules.rst
docs/usage.rst
notebooks/2d_gauss.ipynb
notebooks/README.rst
notebooks/dual_abc_pmc.ipynb
notebooks/toy_model.ipynb
test/__init__.py
test/test_MpiUtil.py
test/test_sampler.py
test/test_threshold.py