Metadata-Version: 1.1
Name: abcpmc
Version: 0.1.2
Summary: approximate bayesian computing with population monte carlo
Home-page: http://www.cosmology.ethz.ch/research/software-lab/abcpmc.html
Author: Joel Akeret
Author-email: jakeret@phys.ethz.ch
License: GPLv3
Keywords: abcpmc,approximate bayesian computing ,population monte carlo
Platform: UNKNOWN
Classifier: Development Status :: 4 - Beta
Classifier: Intended Audience :: Science/Research
Classifier: Intended Audience :: Developers
Classifier: License :: OSI Approved :: GNU General Public License v3 or later (GPLv3+)
Classifier: Natural Language :: English
Classifier: Operating System :: MacOS
Classifier: Operating System :: POSIX
Classifier: Topic :: Scientific/Engineering
Classifier: Topic :: Scientific/Engineering :: Mathematics
Classifier: Topic :: Scientific/Engineering :: Physics
Classifier: Topic :: Scientific/Engineering :: Astronomy
Classifier: Programming Language :: Python :: 2.6
Classifier: Programming Language :: Python :: 2.7
Classifier: Programming Language :: Python :: 3
Classifier: Programming Language :: Python :: 3.3
